LICENSE
README.md
lyyimage.py
setup.py
lyyimage.egg-info/PKG-INFO
lyyimage.egg-info/SOURCES.txt
lyyimage.egg-info/dependency_links.txt
lyyimage.egg-info/requires.txt
lyyimage.egg-info/top_level.txt